COPYING
MANIFEST.in
README.rst
buildout.cfg
pyproject.toml
requirements.txt
setup.py
version.txt
bob/__init__.py
bob.med.tb.egg-info/PKG-INFO
bob.med.tb.egg-info/SOURCES.txt
bob.med.tb.egg-info/dependency_links.txt
bob.med.tb.egg-info/entry_points.txt
bob.med.tb.egg-info/not-zip-safe
bob.med.tb.egg-info/requires.txt
bob.med.tb.egg-info/top_level.txt
bob/med/__init__.py
bob/med/tb/__init__.py
bob/med/tb/configs/__init__.py
bob/med/tb/configs/datasets/__init__.py
bob/med/tb/configs/datasets/hivtb/__init__.py
bob/med/tb/configs/datasets/hivtb/fold_0.py
bob/med/tb/configs/datasets/hivtb/fold_0_rgb.py
bob/med/tb/configs/datasets/hivtb/fold_1.py
bob/med/tb/configs/datasets/hivtb/fold_1_rgb.py
bob/med/tb/configs/datasets/hivtb/fold_2.py
bob/med/tb/configs/datasets/hivtb/fold_2_rgb.py
bob/med/tb/configs/datasets/hivtb/fold_3.py
bob/med/tb/configs/datasets/hivtb/fold_3_rgb.py
bob/med/tb/configs/datasets/hivtb/fold_4.py
bob/med/tb/configs/datasets/hivtb/fold_4_rgb.py
bob/med/tb/configs/datasets/hivtb/fold_5.py
bob/med/tb/configs/datasets/hivtb/fold_5_rgb.py
bob/med/tb/configs/datasets/hivtb/fold_6.py
bob/med/tb/configs/datasets/hivtb/fold_6_rgb.py
bob/med/tb/configs/datasets/hivtb/fold_7.py
bob/med/tb/configs/datasets/hivtb/fold_7_rgb.py
bob/med/tb/configs/datasets/hivtb/fold_8.py
bob/med/tb/configs/datasets/hivtb/fold_8_rgb.py
bob/med/tb/configs/datasets/hivtb/fold_9.py
bob/med/tb/configs/datasets/hivtb/fold_9_rgb.py
bob/med/tb/configs/datasets/hivtb_RS/__init__.py
bob/med/tb/configs/datasets/hivtb_RS/fold_0.py
bob/med/tb/configs/datasets/hivtb_RS/fold_1.py
bob/med/tb/configs/datasets/hivtb_RS/fold_2.py
bob/med/tb/configs/datasets/hivtb_RS/fold_3.py
bob/med/tb/configs/datasets/hivtb_RS/fold_4.py
bob/med/tb/configs/datasets/hivtb_RS/fold_5.py
bob/med/tb/configs/datasets/hivtb_RS/fold_6.py
bob/med/tb/configs/datasets/hivtb_RS/fold_7.py
bob/med/tb/configs/datasets/hivtb_RS/fold_8.py
bob/med/tb/configs/datasets/hivtb_RS/fold_9.py
bob/med/tb/configs/datasets/indian/__init__.py
bob/med/tb/configs/datasets/indian/default.py
bob/med/tb/configs/datasets/indian/fold_0.py
bob/med/tb/configs/datasets/indian/fold_0_rgb.py
bob/med/tb/configs/datasets/indian/fold_1.py
bob/med/tb/configs/datasets/indian/fold_1_rgb.py
