Metadata-Version: 2.1
Name: bob.med.tb
Version: 1.0.2
Summary: Active Pulmonary Tuberculosis Detection On Chest X-Rays
Home-page: https://gitlab.idiap.ch/bob/bob.med.tb
Author: Geoffrey Raposo
Author-email: geoffrey@raposo.ch
Maintainer: Andre Anjos
Maintainer-email: andre.anjos@idiap.ch
License: GPLv3
Keywords: bob
Platform: UNKNOWN
Classifier: Framework :: Bob
Classifier: Development Status :: 4 - Beta
Classifier: Intended Audience :: Science/Research
Classifier: License :: OSI Approved :: GNU General Public License v3 (GPLv3)
Classifier: Natural Language :: English
Classifier: Programming Language :: Python
Classifier: Programming Language :: Python :: 3
Classifier: Topic :: Scientific/Engineering :: Artificial Intelligence
Classifier: Topic :: Software Development :: Libraries :: Python Modules
License-File: COPYING
